geolib_plus/__init__.py
geolib_plus/bro_xml_cpt/__init__.py
geolib_plus/bro_xml_cpt/bro_utils.py
geolib_plus/bro_xml_cpt/bro_xml_cpt.py
geolib_plus/bro_xml_cpt/validate_bro.py
geolib_plus/cpt_base_model.py
geolib_plus/cpt_utils/__init__.py
geolib_plus/cpt_utils/cpt_utils.py
geolib_plus/cpt_utils/NEN9997.py
geolib_plus/cpt_utils/pwp_reader.py
geolib_plus/cpt_utils/resources/NEN9997.json
geolib_plus/gef_cpt/__init__.py
geolib_plus/gef_cpt/gef_cpt.py
geolib_plus/gef_cpt/gef_file_reader.py
geolib_plus/gef_cpt/resources/geflib.dll
geolib_plus/gef_cpt/resources/libgeflib.so.1
geolib_plus/gef_cpt/validate_gef.py
geolib_plus/geolib_connections.py
geolib_plus/hardening_soil_model_parameters.py
geolib_plus/plot_cpt.py
geolib_plus/plot_dynamic_map.py
geolib_plus/plot_settings.py
geolib_plus/plot_utils.py
geolib_plus/relative_density_correlated_parametes.py
geolib_plus/robertson_cpt_interpretation/__init__.py
geolib_plus/robertson_cpt_interpretation/resources/peilgebieden_jp_250m.nc
geolib_plus/robertson_cpt_interpretation/resources/Robertson.dbf
geolib_plus/robertson_cpt_interpretation/resources/Robertson.shp
geolib_plus/robertson_cpt_interpretation/resources/Robertson.shx
geolib_plus/robertson_cpt_interpretation/robertson_cpt_interpretation.py
geolib_plus/shm/__init__.py
geolib_plus/shm/general_utils.py
geolib_plus/shm/nkt_utils.py
geolib_plus/shm/prob_utils.py
geolib_plus/shm/resources/shm_tables.json
geolib_plus/shm/shansep_utils.py
geolib_plus/shm/shm_tables.py
geolib_plus/shm/soil.py
geolib_plus/shm/state_utils.py
geolib_plus/soft_soil_creep_parameters.py
d_geolib_plus-0.4.1.dist-info/METADATA
d_geolib_plus-0.4.1.dist-info/WHEEL
d_geolib_plus-0.4.1.dist-info/RECORD
