Metadata-Version: 2.3
Name: d-geolib-plus
Version: 0.4.1
Summary: GEOLib+ components
License: LGPL-3.0-or-later
Author: Maarten Pronk
Author-email: git@evetion.nl
Requires-Python: >=3.9,<3.13
Classifier: License :: OSI Approved :: GNU Lesser General Public License v3 or later (LGPLv3+)
Classifier: Programming Language :: Python :: 3
Classifier: Programming Language :: Python :: 3.9
Classifier: Programming Language :: Python :: 3.10
Classifier: Programming Language :: Python :: 3.11
Classifier: Programming Language :: Python :: 3.12
Requires-Dist: d-geolib (>=1.3.3,<3.0.0)
Requires-Dist: lxml (>=4.9.3,<5.0.0)
Requires-Dist: matplotlib (>=3.8.1,<4.0.0)
Requires-Dist: more-itertools (>=10.1.0,<11.0.0)
Requires-Dist: netCDF4 (>=1.6.5,<2.0.0)
Requires-Dist: numpy (>=1.26.2,<3.0.0)
Requires-Dist: pandas (>=2.1.3,<3.0.0)
Requires-Dist: pydantic (>=1,<2)
Requires-Dist: pyproj (>=3.6.1,<4.0.0)
Requires-Dist: pyshp (>=2.3.1,<3.0.0)
Requires-Dist: requests (>=2.26,<3.0)
Requires-Dist: scipy (>=1.11.3,<2.0.0)
Requires-Dist: seaborn (>=0.13.0,<0.14.0)
Requires-Dist: shapely (>=2.0.2,<3.0.0)
Requires-Dist: sphinx-math-dollar (>=1.2.1,<2.0.0)
Requires-Dist: tqdm (>=4.66.1,<5.0.0)
Project-URL: Documentation, https://deltares.github.io/geolib-plus/
Project-URL: Homepage, https://deltares.github.io/geolib-plus/
Project-URL: Repository, https://github.com/Deltares/geolib-plus
